Metadata-Version: 2.1
Name: tputils
Version: 0.0.1
Summary: Utilities for TPUs.
Home-page: https://github.com/sdtblck/tputils
Author: Sid Black
Author-email: sdtblck@gmail.com
License: MIT
Platform: UNKNOWN
Classifier: License :: OSI Approved :: MIT License
Classifier: Programming Language :: Python :: 3.6
